<?xml version="1.0" encoding="utf-8" ?>
<dwsync>
<file name="grid.base.js" server="ftp.superprofessorweb.com.br/public_html/interbits/" local="129966756194390000" remote="130003272600000000" />
<file name="grid.celledit.js" server="ftp.superprofessorweb.com.br/public_html/interbits/" local="129966756334900000" remote="130003272600000000" />
<file name="grid.common.js" server="ftp.superprofessorweb.com.br/public_html/interbits/" local="129966756229430000" remote="130003272600000000" />
<file name="grid.custom.js" server="ftp.superprofessorweb.com.br/public_html/interbits/" local="129966756352840000" remote="130003272600000000" />
<file name="grid.filter.js" server="ftp.superprofessorweb.com.br/public_html/interbits/" local="129966756318420000" remote="130003272600000000" />
<file name="grid.formedit.js" server="ftp.superprofessorweb.com.br/public_html/interbits/" local="129966756223540000" remote="130003272600000000" />
<file name="grid.grouping.js" server="ftp.superprofessorweb.com.br/public_html/interbits/" local="129966756257360000" remote="130003272600000000" />
<file name="grid.import.js" server="ftp.superprofessorweb.com.br/public_html/interbits/" local="129966756242950000" remote="130003272600000000" />
<file name="grid.inlinedit.js" server="ftp.superprofessorweb.com.br/public_html/interbits/" local="129966756229490000" remote="130003272600000000" />
<file name="grid.jqueryui.js" server="ftp.superprofessorweb.com.br/public_html/interbits/" local="129966756365420000" remote="130003272600000000" />
<file name="grid.loader.js" server="ftp.superprofessorweb.com.br/public_html/interbits/" local="129966756297500000" remote="130003272600000000" />
<file name="grid.subgrid.js" server="ftp.superprofessorweb.com.br/public_html/interbits/" local="129966756221070000" remote="130003272600000000" />
<file name="grid.tbltogrid.js" server="ftp.superprofessorweb.com.br/public_html/interbits/" local="129966756252910000" remote="130003272600000000" />
<file name="grid.treegrid.js" server="ftp.superprofessorweb.com.br/public_html/interbits/" local="129966756346780000" remote="130003272600000000" />
<file name="jqDnR.js" server="ftp.superprofessorweb.com.br/public_html/interbits/" local="129966756217660000" remote="130003272600000000" />
<file name="jqModal.js" server="ftp.superprofessorweb.com.br/public_html/interbits/" local="129966756348310000" remote="130003272600000000" />
<file name="jquery.fmatter.js" server="ftp.superprofessorweb.com.br/public_html/interbits/" local="129966756365520000" remote="130003272600000000" />
<file name="JsonXml.js" server="ftp.superprofessorweb.com.br/public_html/interbits/" local="129966756318580000" remote="130003272600000000" />
</dwsync>