<?xml version="1.0" encoding="utf-8" ?>
<dwsync>
<file name="admin-bar-sprite.png" server="ftp.supervip.com.br/public_html/" local="130095676367360000" remote="129734028000000000" Dst="1" />
<file name="arrow-pointer-blue.png" server="ftp.supervip.com.br/public_html/" local="130095676367380000" remote="129734028000000000" Dst="1" />
<file name="blank.gif" server="ftp.supervip.com.br/public_html/" local="130095676367950000" remote="129734028000000000" Dst="1" />
<file name="down_arrow.gif" server="ftp.supervip.com.br/public_html/" local="130095676372510000" remote="129734028000000000" Dst="1" />
<file name="rss.png" server="ftp.supervip.com.br/public_html/" local="130095676374180000" remote="129734028000000000" Dst="1" />
<file name="icon-pointer-flag.png" server="ftp.supervip.com.br/public_html/" local="130095676374190000" remote="129734028000000000" Dst="1" />
<file name="toggle-arrow.png" server="ftp.supervip.com.br/public_html/" local="130095676381870000" remote="129734028000000000" Dst="1" />
<file name="upload.png" server="ftp.supervip.com.br/public_html/" local="130095676382730000" remote="129734028000000000" Dst="1" />
<file name="wpicons.png" server="ftp.supervip.com.br/public_html/" local="130095676383990000" remote="129734028000000000" Dst="1" />
<file name="wpmini-blue.png" server="ftp.supervip.com.br/public_html/" local="130095676384560000" remote="129734028000000000" Dst="1" />
<file name="xit.gif" server="ftp.supervip.com.br/public_html/" local="130095676384580000" remote="129734028000000000" Dst="1" />
</dwsync>