<?xml version="1.0" encoding="utf-8" ?>
<dwsync>
<file name="install.xml" server="ftp.superprofessorweb.com.br/public_html/interbits/" local="129986073650475000" remote="130003273800000000" />
<file name="jquery_ui_1_8_23_custom_min.css" server="ftp.superprofessorweb.com.br/public_html/interbits/" local="129966756197070000" remote="130003273800000000" />
<file name="jquery_ui_1_8_23_custom_min.js" server="ftp.superprofessorweb.com.br/public_html/interbits/" local="129966756219800000" remote="130003273800000000" />
<file name="jquery_ui_1_9_1_custom_min.css" server="ftp.superprofessorweb.com.br/public_html/interbits/" local="129978286161180000" remote="130003273800000000" />
<file name="jquery_ui_1_9_1_custom_min.js" server="ftp.superprofessorweb.com.br/public_html/interbits/" local="129968539650390000" remote="130003273800000000" />
<file name="jquery_ui_1_9_2_custom.css" server="ftp.superprofessorweb.com.br/public_html/interbits/" local="129986073650495000" remote="130003273800000000" />
<file name="jquery_ui_1_9_2_custom_min.css" server="ftp.superprofessorweb.com.br/public_html/interbits/" local="129986073649760000" remote="130003273800000000" />
<file name="jquery_ui_datepicker_pt_BR.js" server="ftp.superprofessorweb.com.br/public_html/interbits/" local="129968539650070000" remote="130003273800000000" />
<file name="_jquery_ui_1_9_2_custom_min.css" server="ftp.superprofessorweb.com.br/public_html/interbits/" local="130003152470400000" remote="130003273800000000" />
<file name="_jquery_ui_datepicker_pt_BR_min.js" server="ftp.superprofessorweb.com.br/public_html/interbits/" local="130003152481995000" remote="130003273800000000" />
</dwsync>